syntaxmatrix/__init__.py
syntaxmatrix/auth.py
syntaxmatrix/bootstrap.py
syntaxmatrix/commentary.py
syntaxmatrix/core.py
syntaxmatrix/dataset_preprocessing.py
syntaxmatrix/db.py
syntaxmatrix/db_contract.py
syntaxmatrix/display_html.py
syntaxmatrix/emailer.py
syntaxmatrix/file_processor.py
syntaxmatrix/gpt_models_latest.py
syntaxmatrix/history_store.py
syntaxmatrix/kernel_manager.py
syntaxmatrix/llm_store.py
syntaxmatrix/models.py
syntaxmatrix/page_builder_defaults.py
syntaxmatrix/page_builder_generation.py
syntaxmatrix/page_layout_contract.py
syntaxmatrix/page_patch_publish.py
syntaxmatrix/plottings.py
syntaxmatrix/plugin_manager.py
syntaxmatrix/preface.py
syntaxmatrix/profiles.py
syntaxmatrix/project_root.py
syntaxmatrix/routes.py
syntaxmatrix/selftest_page_templates.py
syntaxmatrix/session.py
syntaxmatrix/smiv.py
syntaxmatrix/smpv.py
syntaxmatrix/themes.py
syntaxmatrix/ui_modes.py
syntaxmatrix/utils.py
syntaxmatrix/vector_db.py
syntaxmatrix/vectorizer.py
syntaxmatrix/workspace_db.py
syntaxmatrix/agentic/__init__.py
syntaxmatrix/agentic/agent_tools.py
syntaxmatrix/agentic/agents.py
syntaxmatrix/agentic/agents_orchestrer.py
syntaxmatrix/agentic/code_tools_registry.py
syntaxmatrix/agentic/model_templates.py
syntaxmatrix/db_backends/__init__.py
syntaxmatrix/db_backends/postgres_backend.py
syntaxmatrix/db_backends/sqlite_backend.py
syntaxmatrix/media/__init__.py
syntaxmatrix/media/media_pixabay.py
syntaxmatrix/premium/__init__.py
syntaxmatrix/premium/gate.py
syntaxmatrix/settings/__init__.py
syntaxmatrix/settings/client_items.py
syntaxmatrix/settings/default.yaml
syntaxmatrix/settings/logging.py
syntaxmatrix/settings/model_map.py
syntaxmatrix/settings/prompts.py
syntaxmatrix/settings/string_navbar.py
syntaxmatrix/static/docs.md
syntaxmatrix/static/assets/hero-default.svg
syntaxmatrix/static/css/style.css
syntaxmatrix/static/icons/bot_icon.png
syntaxmatrix/static/icons/favicon.png
syntaxmatrix/static/icons/logo.png
syntaxmatrix/static/icons/logo3.png
syntaxmatrix-2.6.4.4.dist-info/licenses/LICENSE.txt
syntaxmatrix-2.6.4.4.dist-info/METADATA
syntaxmatrix-2.6.4.4.dist-info/WHEEL
syntaxmatrix-2.6.4.4.dist-info/top_level.txt
syntaxmatrix-2.6.4.4.dist-info/RECORD
