Metadata-Version: 2.4
Name: syntaxmatrix
Version: 2.6.4.4
Summary: SyntaxMUI: A customizable framework for Python AI Assistant Projects.
Author: Bob Nti
Author-email: bob.nti@syntaxmatrix.net
License: MIT
Classifier: Programming Language :: Python :: 3.9
Classifier: Operating System :: OS Independent
Requires-Python: >=3.9
License-File: LICENSE.txt
Requires-Dist: Flask>=3.0.3
Requires-Dist: requests>=2.32.3
Requires-Dist: pytz<2026,>=2025.2
Requires-Dist: pywin32>=311; sys_platform == "win32"
Requires-Dist: Markdown>=3.7
Requires-Dist: pypdf>=5.4.0
Requires-Dist: PyPDF2==3.0.1
Requires-Dist: nest-asyncio>=1.6.0
Requires-Dist: python-dotenv>=1.1.0
Requires-Dist: openai>=1.84.0
Requires-Dist: google-genai>=1.19.0
Requires-Dist: anthropic>=0.67.0
Requires-Dist: reportlab>=4.4.3
Requires-Dist: lxml>=6.0.2
Requires-Dist: flask-login>=0.6.3
Requires-Dist: pandas>=2.2.3
Requires-Dist: numpy>=2.0.2
Requires-Dist: matplotlib>=3.9.4
Requires-Dist: plotly>=6.3.0
Requires-Dist: seaborn>=0.13.2
Requires-Dist: scikit-learn>=1.6.1
Requires-Dist: jupyter_client>=8.6.3
Requires-Dist: ipykernel>=6.29.5
Requires-Dist: ipython
Requires-Dist: statsmodels
Requires-Dist: sqlalchemy>=2.0.42
Requires-Dist: cryptography>=45.0.6
Requires-Dist: regex>=2025.11.3
Requires-Dist: tiktoken>=0.12.0
Requires-Dist: xgboost>=2.1.4
Requires-Dist: beautifulsoup4>=4.12.2
Requires-Dist: html5lib>=1.1
Requires-Dist: shap>=0.42.0
Dynamic: author
Dynamic: author-email
Dynamic: classifier
Dynamic: description
Dynamic: description-content-type
Dynamic: license
Dynamic: license-file
Dynamic: requires-dist
Dynamic: requires-python
Dynamic: summary
